MANIFEST.in
README.rst
setup.py
sebflow/__init__.py
sebflow/configuration.py
sebflow/exceptions.py
sebflow/logging_config.py
sebflow/models.py
sebflow/settings.py
sebflow/state.py
sebflow/timezone.py
sebflow.egg-info/PKG-INFO
sebflow.egg-info/SOURCES.txt
sebflow.egg-info/dependency_links.txt
sebflow.egg-info/entry_points.txt
sebflow.egg-info/requires.txt
sebflow.egg-info/top_level.txt
sebflow/bin/__init__.py
sebflow/bin/cli.py
sebflow/bin/sebflow
sebflow/bin/sebflow.py
sebflow/config_files/__init__.py
sebflow/config_files/create_tables_mssql.sql
sebflow/config_files/create_tables_postgres.sql
sebflow/config_files/sebflow.cfg
sebflow/executors/__init__.py
sebflow/executors/base_executor.py
sebflow/executors/local_executor.py
sebflow/hooks/__init__.py
sebflow/hooks/base_hook.py
sebflow/hooks/dbapi_hook.py
sebflow/hooks/mssql_hook.py
sebflow/operators/__init__.py
sebflow/operators/mssql_operator.py
sebflow/operators/python_operator.py
sebflow/utils/__init__.py
sebflow/utils/db.py
sebflow/utils/decorators.py
sebflow/utils/log/__init__.py
sebflow/utils/log/logging_mixin.py