Metadata-Version: 1.0
Name: sebflow
Version: 0.0.2
Summary: programatically author and monitor data pipelines
Home-page: https://github.com/estenssoros/sebflow
Author: Sebastian Estenssoro
Author-email: seb.estenssoro@gmail.com
License: MIT
Platform: UNKNOWN
